data_entry_demo/__init__.py
data_entry_demo/data_entry_demo.py
data_entry_demo-0.0.1.dist-info/METADATA
data_entry_demo-0.0.1.dist-info/WHEEL
data_entry_demo-0.0.1.dist-info/top_level.txt
data_entry_demo-0.0.1.dist-info/RECORD
