Metadata-Version: 2.1
Name: data-entry-demo
Version: 0.0.1
Summary: package to demo CHR data entry
Home-page: UNKNOWN
Author: adam
Author-email: adam.kehoe@opexanalytics.com
License: UNKNOWN
Platform: UNKNOWN
Classifier: Programming Language :: Python :: 3
